MANIFEST.in
README.md
setup.py
asyncmrq/__init__.py
asyncmrq/client.py
asyncmrq/errors.py
asyncmrq/parser.py
asyncmrq.egg-info/PKG-INFO
asyncmrq.egg-info/SOURCES.txt
asyncmrq.egg-info/dependency_links.txt
asyncmrq.egg-info/top_level.txt
asyncmrq.egg-info/zip-safe